kraken_wsclient_v2/__init__.py
kraken_wsclient_v2/kraken_wsclient_v2.py
kraken_wsclient_v2-0.0.2.dist-info/LICENSE.txt
kraken_wsclient_v2-0.0.2.dist-info/METADATA
kraken_wsclient_v2-0.0.2.dist-info/WHEEL
kraken_wsclient_v2-0.0.2.dist-info/top_level.txt
kraken_wsclient_v2-0.0.2.dist-info/RECORD
