Metadata-Version: 2.1
Name: kraken-wsclient-v2
Version: 0.0.2
Summary: Sample Kraken WebSockets client V2
Author: Kraken
Author-email: engineering@kraken.com
License: MIT
Keywords: kraken websockets v2
Classifier: Development Status :: 3 - Alpha
Classifier: Intended Audience :: Developers
Classifier: License :: OSI Approved :: MIT License
Classifier: Programming Language :: Python :: 3
Requires-Python: >=3
License-File: LICENSE.txt
Requires-Dist: autobahn ==23.1.2
Requires-Dist: hyperlink ==21.0.0
Requires-Dist: Twisted ==22.4.0
